[
  {
    "platform": "levels_fyi",
    "raw_content": "Software Engineer L6 | Base 39万 | Bonus 13万",
    "raw_location": "Global"
  },
  {
    "platform": "levels_fyi",
    "raw_content": "Software Engineer L3 | Base 58万 | Bonus 12万",
    "raw_location": "Global"
  },
  {
    "platform": "levels_fyi",
    "raw_content": "Software Engineer L3 | Base 45万 | Bonus 13万",
    "raw_location": "Global"
  },
  {
    "platform": "levels_fyi",
    "raw_content": "Software Engineer L4 | Base 52万 | Bonus 12万",
    "raw_location": "Global"
  },
  {
    "platform": "levels_fyi",
    "raw_content": "Software Engineer L6 | Base 59万 | Bonus 17万",
    "raw_location": "Global"
  },
  {
    "platform": "levels_fyi",
    "raw_content": "Software Engineer L6 | Base 57万 | Bonus 11万",
    "raw_location": "Global"
  },
  {
    "platform": "levels_fyi",
    "raw_content": "Software Engineer L6 | Base 46万 | Bonus 18万",
    "raw_location": "Global"
  },
  {
    "platform": "levels_fyi",
    "raw_content": "Software Engineer L4 | Base 78万 | Bonus 8万",
    "raw_location": "Global"
  },
  {
    "platform": "levels_fyi",
    "raw_content": "Software Engineer L4 | Base 59万 | Bonus 13万",
    "raw_location": "Global"
  },
  {
    "platform": "levels_fyi",
    "raw_content": "Software Engineer L4 | Base 71万 | Bonus 11万",
    "raw_location": "Global"
  },
  {
    "platform": "levels_fyi",
    "raw_content": "Software Engineer L4 | Base 52万 | Bonus 18万",
    "raw_location": "Global"
  },
  {
    "platform": "levels_fyi",
    "raw_content": "Software Engineer L3 | Base 48万 | Bonus 7万",
    "raw_location": "Global"
  },
  {
    "platform": "levels_fyi",
    "raw_content": "Software Engineer L6 | Base 63万 | Bonus 5万",
    "raw_location": "Global"
  },
  {
    "platform": "levels_fyi",
    "raw_content": "Software Engineer L3 | Base 37万 | Bonus 17万",
    "raw_location": "Global"
  },
  {
    "platform": "levels_fyi",
    "raw_content": "Software Engineer L6 | Base 73万 | Bonus 18万",
    "raw_location": "Global"
  },
  {
    "platform": "levels_fyi",
    "raw_content": "Software Engineer L6 | Base 62万 | Bonus 8万",
    "raw_location": "Global"
  },
  {
    "platform": "levels_fyi",
    "raw_content": "Software Engineer L5 | Base 60万 | Bonus 11万",
    "raw_location": "Global"
  },
  {
    "platform": "levels_fyi",
    "raw_content": "Software Engineer L5 | Base 54万 | Bonus 7万",
    "raw_location": "Global"
  },
  {
    "platform": "levels_fyi",
    "raw_content": "Software Engineer L4 | Base 46万 | Bonus 14万",
    "raw_location": "Global"
  },
  {
    "platform": "levels_fyi",
    "raw_content": "Software Engineer L4 | Base 70万 | Bonus 15万",
    "raw_location": "Global"
  },
  {
    "platform": "levels_fyi",
    "raw_content": "Software Engineer L3 | Base 46万 | Bonus 11万",
    "raw_location": "Global"
  },
  {
    "platform": "levels_fyi",
    "raw_content": "Software Engineer L5 | Base 63万 | Bonus 15万",
    "raw_location": "Global"
  },
  {
    "platform": "levels_fyi",
    "raw_content": "Software Engineer L5 | Base 57万 | Bonus 14万",
    "raw_location": "Global"
  },
  {
    "platform": "levels_fyi",
    "raw_content": "Software Engineer L5 | Base 30万 | Bonus 16万",
    "raw_location": "Global"
  },
  {
    "platform": "levels_fyi",
    "raw_content": "Software Engineer L3 | Base 36万 | Bonus 15万",
    "raw_location": "Global"
  },
  {
    "platform": "levels_fyi",
    "raw_content": "Software Engineer L4 | Base 35万 | Bonus 12万",
    "raw_location": "Global"
  },
  {
    "platform": "levels_fyi",
    "raw_content": "Software Engineer L4 | Base 44万 | Bonus 16万",
    "raw_location": "Global"
  },
  {
    "platform": "levels_fyi",
    "raw_content": "Software Engineer L3 | Base 73万 | Bonus 17万",
    "raw_location": "Global"
  },
  {
    "platform": "levels_fyi",
    "raw_content": "Software Engineer L6 | Base 34万 | Bonus 17万",
    "raw_location": "Global"
  },
  {
    "platform": "levels_fyi",
    "raw_content": "Software Engineer L4 | Base 45万 | Bonus 7万",
    "raw_location": "Global"
  },
  {
    "platform": "levels_fyi",
    "raw_content": "Software Engineer L6 | Base 64万 | Bonus 6万",
    "raw_location": "Global"
  },
  {
    "platform": "levels_fyi",
    "raw_content": "Software Engineer L6 | Base 56万 | Bonus 17万",
    "raw_location": "Global"
  },
  {
    "platform": "levels_fyi",
    "raw_content": "Software Engineer L6 | Base 62万 | Bonus 14万",
    "raw_location": "Global"
  },
  {
    "platform": "levels_fyi",
    "raw_content": "Software Engineer L3 | Base 72万 | Bonus 14万",
    "raw_location": "Global"
  },
  {
    "platform": "levels_fyi",
    "raw_content": "Software Engineer L3 | Base 74万 | Bonus 14万",
    "raw_location": "Global"
  },
  {
    "platform": "levels_fyi",
    "raw_content": "Software Engineer L5 | Base 75万 | Bonus 17万",
    "raw_location": "Global"
  },
  {
    "platform": "levels_fyi",
    "raw_content": "Software Engineer L4 | Base 56万 | Bonus 7万",
    "raw_location": "Global"
  },
  {
    "platform": "levels_fyi",
    "raw_content": "Software Engineer L5 | Base 37万 | Bonus 20万",
    "raw_location": "Global"
  },
  {
    "platform": "levels_fyi",
    "raw_content": "Software Engineer L5 | Base 69万 | Bonus 10万",
    "raw_location": "Global"
  },
  {
    "platform": "levels_fyi",
    "raw_content": "Software Engineer L5 | Base 72万 | Bonus 19万",
    "raw_location": "Global"
  },
  {
    "platform": "levels_fyi",
    "raw_content": "Software Engineer L4 | Base 39万 | Bonus 7万",
    "raw_location": "Global"
  },
  {
    "platform": "levels_fyi",
    "raw_content": "Software Engineer L5 | Base 51万 | Bonus 11万",
    "raw_location": "Global"
  },
  {
    "platform": "levels_fyi",
    "raw_content": "Software Engineer L3 | Base 73万 | Bonus 13万",
    "raw_location": "Global"
  },
  {
    "platform": "levels_fyi",
    "raw_content": "Software Engineer L5 | Base 45万 | Bonus 19万",
    "raw_location": "Global"
  },
  {
    "platform": "levels_fyi",
    "raw_content": "Software Engineer L3 | Base 39万 | Bonus 12万",
    "raw_location": "Global"
  },
  {
    "platform": "levels_fyi",
    "raw_content": "Software Engineer L4 | Base 79万 | Bonus 14万",
    "raw_location": "Global"
  },
  {
    "platform": "levels_fyi",
    "raw_content": "Software Engineer L6 | Base 38万 | Bonus 16万",
    "raw_location": "Global"
  },
  {
    "platform": "levels_fyi",
    "raw_content": "Software Engineer L4 | Base 52万 | Bonus 20万",
    "raw_location": "Global"
  },
  {
    "platform": "levels_fyi",
    "raw_content": "Software Engineer L6 | Base 74万 | Bonus 5万",
    "raw_location": "Global"
  },
  {
    "platform": "levels_fyi",
    "raw_content": "Software Engineer L3 | Base 72万 | Bonus 9万",
    "raw_location": "Global"
  },
  {
    "platform": "levels_fyi",
    "raw_content": "Software Engineer L6 | Base 80万 | Bonus 13万",
    "raw_location": "Global"
  },
  {
    "platform": "levels_fyi",
    "raw_content": "Software Engineer L4 | Base 37万 | Bonus 8万",
    "raw_location": "Global"
  },
  {
    "platform": "levels_fyi",
    "raw_content": "Software Engineer L6 | Base 60万 | Bonus 20万",
    "raw_location": "Global"
  },
  {
    "platform": "levels_fyi",
    "raw_content": "Software Engineer L4 | Base 37万 | Bonus 9万",
    "raw_location": "Global"
  },
  {
    "platform": "levels_fyi",
    "raw_content": "Software Engineer L4 | Base 39万 | Bonus 10万",
    "raw_location": "Global"
  }
]